hrun/__init__.py
hrun/hrun.cpython-311-i386-linux-gnu.so
hrun/hrun.pyi
hrun/types.py
hrun_rt-0.1.2.dist-info/METADATA
hrun_rt-0.1.2.dist-info/WHEEL
hrun_rt-0.1.2.dist-info/licenses/LICENSE
hrun_rt-0.1.2.dist-info/RECORD
