Metadata-Version: 2.4
Name: hrun-rt
Version: 0.1.2
Classifier: Programming Language :: Rust
Classifier: Programming Language :: Python :: Implementation :: CPython
Classifier: Programming Language :: Python :: Implementation :: PyPy
Requires-Dist: pytest ; extra == 'tests'
Provides-Extra: tests
License-File: LICENSE
Summary: H is a simple runtime designed to be fast and memory-safe.
Requires-Python: >=3.8
Project-URL: Source, https://github.com/AWeirdDev/hrun
Project-URL: Issues, https://github.com/AWeirdDev/hrun/issues
